txoauth2/__init__.py
txoauth2/authorization.py
txoauth2/clients.py
txoauth2/errors.py
txoauth2/granttypes.py
txoauth2/imp.py
txoauth2/resource.py
txoauth2/token.py
txoauth2/util.py
txoauth2-1.2.1.dist-info/LICENSE
txoauth2-1.2.1.dist-info/METADATA
txoauth2-1.2.1.dist-info/WHEEL
txoauth2-1.2.1.dist-info/top_level.txt
txoauth2-1.2.1.dist-info/RECORD
